{"cameraMode":{"drawMode":0,"name":"Shaded","section":"Shading Mode"},"sceneLighting":true,"audioPlay":false,"sceneViewState":{"showFog":true,"showMaterialUpdate":false,"showSkybox":true,"showFlares":true,"showImageEffects":true,"showParticleSystems":true},"in2DMode":false,"pivot":{"x":3.028303623199463,"y":-0.6927101612091065,"z":-1.4616420269012452},"rotation":{"x":0.0830954909324646,"y":0.83823561668396,"z":-0.1333928108215332,"w":0.5221710205078125},"size":5.301825523376465,"orthographic":false}